audio2topics/__init__.py
audio2topics/main.py
audio2topics/core/__init__.py
audio2topics/core/llm_service.py
audio2topics/core/secure_config.py
audio2topics/core/text_processor.py
audio2topics/core/topic_modeler.py
audio2topics/core/transcriber.py
audio2topics/core/validator.py
audio2topics/core/visualizer.py
audio2topics/resources/icons/GUI.svg
audio2topics/resources/icons/app_icon.png
audio2topics/resources/icons/open_folder.svg
audio2topics/ui/__init__.py
audio2topics/ui/comparison_tab.py
audio2topics/ui/main_window.py
audio2topics/ui/processor_tab.py
audio2topics/ui/settings_dialog.py
audio2topics/ui/topic_tab.py
audio2topics/ui/transcriber_tab.py
audio2topics/ui/validator_tab.py
audio2topics/ui/visualizer_tab.py
audio2topics/utils/__init__.py
audio2topics/utils/config.py
audio2topics/utils/logger.py
audio2topics/utils/resource_checker.py
audio2topics-1.1.2.dist-info/LICENSE.txt
audio2topics-1.1.2.dist-info/METADATA
audio2topics-1.1.2.dist-info/WHEEL
audio2topics-1.1.2.dist-info/entry_points.txt
audio2topics-1.1.2.dist-info/top_level.txt
audio2topics-1.1.2.dist-info/RECORD
