Metadata-Version: 2.1
Name: audio2topics
Version: 1.1.2
Summary: Extract topics directly from audio or text and text files
Author: Mohsen Askar
Author-email: ceaser198511@gmail.com
Classifier: Development Status :: 4 - Beta
Classifier: Environment :: X11 Applications :: Qt
Classifier: Intended Audience :: Science/Research
Classifier: License :: OSI Approved :: MIT License
Classifier: Programming Language :: Python :: 3
Classifier: Programming Language :: Python :: 3.10
Classifier: Programming Language :: Python :: 3.11
Classifier: Programming Language :: Python :: 3.12
Classifier: Topic :: Multimedia :: Sound/Audio :: Speech
Classifier: Topic :: Scientific/Engineering :: Artificial Intelligence
Classifier: Topic :: Text Processing :: Linguistic
Requires-Python: >=3.10
License-File: LICENSE.txt
Requires-Dist: PyQt5>=5.15.11
Requires-Dist: numpy>=1.20.0
Requires-Dist: pandas>=1.2.0
Requires-Dist: matplotlib>=3.4.0
Requires-Dist: openai-whisper==20240930
Requires-Dist: nltk<3.10.0,>=3.8.0
Requires-Dist: spacy>=3.1.0
Requires-Dist: bertopic>=0.16.4
Requires-Dist: wordcloud>=1.8.0
Requires-Dist: scikit-learn==1.3.2
Requires-Dist: python-docx>=0.8.10
Requires-Dist: requests>=2.28.0
Requires-Dist: torch==2.6.0
Requires-Dist: sentence-transformers==3.4.1
Requires-Dist: pyLDAvis==3.4.1
Requires-Dist: gensim==4.3.3
Requires-Dist: PyQtWebEngine==5.15.7
Requires-Dist: PyQtWebEngine-Qt5==5.15.2
Requires-Dist: umap-learn==0.5.7
Requires-Dist: seaborn>=0.12.0
Requires-Dist: hdbscan==0.8.40
Requires-Dist: scipy>=1.10.0
